MANIFEST
README
hypercode.py
hypercode_server.py
setup.cfg
setup.py
hypercode.egg-info/PKG-INFO
hypercode.egg-info/SOURCES.txt
hypercode.egg-info/dependency_links.txt
hypercode.egg-info/top_level.txt