Metadata-Version: 1.0
Name: hypercode
Version: 0.2a5
Summary: ...
Home-page: http://eikeon.com/2008/hypercode/
Author: Daniel Krech
Author-email: eikeon@eikeon.com
License: UNKNOWN
Platform: UNKNOWN
